AltTesterLibrary/AltTesterKeywords.py
AltTesterLibrary/__init__.py
AltTesterLibrary/version.py
alttester_robotframework_library-2.2.7.dist-info/METADATA
alttester_robotframework_library-2.2.7.dist-info/WHEEL
alttester_robotframework_library-2.2.7.dist-info/top_level.txt
alttester_robotframework_library-2.2.7.dist-info/RECORD
