Metadata-Version: 2.4
Name: alttester-robotframework-library
Version: 2.2.7
Summary: Robot Framework Library for the AltTester® framework. AltTester® is an open-source UI driven test automation tool that helps you find objects in your game and interacts with them.
Home-page: https://alttester.com/docs/sdk/latest/
Author: Altom Consulting
Author-email: contact@alttester.com
License: GNU GPLv3
Project-URL: Issues, https://github.com/alttester/AltTester-Unity-SDK/issues
Project-URL: Documentation, https://alttester.com/docs/sdk/latest
Project-URL: Source, https://github.com/alttester/AltTester-Unity-SDK
Keywords: robot framework testing test automation alttester
Classifier: Development Status :: 5 - Production/Stable
Classifier: Intended Audience :: Developers
Classifier: Intended Audience :: Other Audience
Classifier: License :: OSI Approved :: GNU General Public License v3 (GPLv3)
Classifier: Programming Language :: Python :: 3.10
Classifier: Operating System :: OS Independent
Classifier: Topic :: Games/Entertainment
Classifier: Topic :: Software Development :: Libraries
Classifier: Topic :: Software Development :: Testing
Classifier: Topic :: Software Development :: Testing :: Acceptance
Classifier: Topic :: Software Development :: Testing :: Unit
Requires-Python: >=3.4.0
Requires-Dist: AltTester-Driver
Requires-Dist: robotframework
Dynamic: author
Dynamic: author-email
Dynamic: classifier
Dynamic: description
Dynamic: description-content-type
Dynamic: home-page
Dynamic: keywords
Dynamic: license
Dynamic: project-url
Dynamic: requires-dist
Dynamic: requires-python
Dynamic: summary
